ExtraTypes/__init__.py
ExtraTypes/snowflake.py
extratypes-0.1.dist-info/METADATA
extratypes-0.1.dist-info/WHEEL
extratypes-0.1.dist-info/top_level.txt
extratypes-0.1.dist-info/RECORD
