Metadata-Version: 2.1
Name: extratypes
Version: 0.1
Summary: This package provides a few extra types for Python. Like "Snowflake".
Home-page: https://github.com/RandomTimeLP/RTS_Documentations
Author: RandomTimeTV
Author-email: dergepanzerte1@gmail.com
License: MIT with required credit to the author.
Keywords: Snowflake
Platform: UNKNOWN
Classifier: Development Status :: 3 - Alpha
Classifier: License :: OSI Approved :: MIT License
Classifier: Programming Language :: Python :: 3.6
Classifier: Programming Language :: Python :: 3.7
Classifier: Programming Language :: Python :: 3.8
Classifier: Programming Language :: Python :: 3.9
Classifier: Programming Language :: Python :: 3.10
Classifier: Programming Language :: Python :: 3.11
Classifier: Programming Language :: Python :: 3.12
Requires-Dist: python-dateutil
